{
  "PathOptions": {
    "IgnoreTail": true
  },
  "PathData":[
    {
      "Node": [
        {
          "NodeName": "data",
          "ToDive": false,
          "ToCombine": false
        }
      ]
    },
    {
      "Node": [
        {
          "NodeName": "l2VlanStats",
          "ToDive": false,
          "ToCombine": false
        }
      ]
    },
    {
      "Node": [
        {
          "NodeName": "attributes",
          "ToDive": false,
          "ToCombine": false
        }
      ]
    }
  ]
}